websearch4ai/__init__.py
websearch4ai/core.py
websearch4ai-0.0.1.dist-info/licenses/LICENSE
websearch4ai-0.0.1.dist-info/METADATA
websearch4ai-0.0.1.dist-info/WHEEL
websearch4ai-0.0.1.dist-info/top_level.txt
websearch4ai-0.0.1.dist-info/RECORD
